streamlit_nested_layout/__init__.py
streamlit_nested_layout/nest.py
streamlit_nested_layout-0.1.4.dist-info/LICENSE
streamlit_nested_layout-0.1.4.dist-info/METADATA
streamlit_nested_layout-0.1.4.dist-info/WHEEL
streamlit_nested_layout-0.1.4.dist-info/top_level.txt
streamlit_nested_layout-0.1.4.dist-info/RECORD
