Metadata-Version: 2.1
Name: streamlit-nested-layout
Version: 0.1.4
Summary: Enables nested layout in streamlit.
Home-page: https://github.com/joy13975/streamlit-nested-layout
Author: Joy Yeh
Author-email: joyyeh.tw@gmail.com
License: Apache 2.0
Classifier: License :: OSI Approved :: MIT License
Classifier: Programming Language :: Python
Classifier: Programming Language :: Python :: 3
Classifier: Programming Language :: Python :: 3.6
Classifier: Programming Language :: Python :: Implementation :: CPython
Classifier: Programming Language :: Python :: Implementation :: PyPy
Requires-Python: >=3.7, !=3.9.7
License-File: LICENSE
Requires-Dist: streamlit>=1.10.0
